disint/__init__.py
disint/clustering.py
disint/embedding.py
disint/io_utils.py
disint/metrics.py
disint/normalization.py
disint/plotting.py
disint-0.1.0.dist-info/licenses/LICENSE
disint-0.1.0.dist-info/METADATA
disint-0.1.0.dist-info/WHEEL
disint-0.1.0.dist-info/top_level.txt
disint-0.1.0.dist-info/RECORD
