Metadata-Version: 2.4
Name: disint
Version: 0.1.0
Summary: Reproducible pipeline for normalization, UMAP/K-means clustering, and cluster quality evaluation
Author: Cong Yi
License: Research-only / non-commercial use. See README for terms.
Requires-Python: >=3.9
License-File: LICENSE
Requires-Dist: pandas<3.0,>=2.0
Requires-Dist: numpy<2.2,>=1.26.0
Requires-Dist: numba<0.61,>=0.58.1
Requires-Dist: umap-learn<0.6,>=0.5.6
Requires-Dist: scikit-learn<1.7,>=1.4
Requires-Dist: matplotlib<3.11,>=3.8
Requires-Dist: optuna<4.0,>=3.0
Dynamic: license-file
